translation/__init__.py
translation/exception.py
translation/main.py
translation/tools.py
translation/models/__init__.py
translation/models/baidu.py
translation/models/bing.py
translation/models/google.py
translation/models/iciba.py
translation/models/language.py
translation/models/youdao.py
translation-1.0.5.dist-info/DESCRIPTION.rst
translation-1.0.5.dist-info/METADATA
translation-1.0.5.dist-info/RECORD
translation-1.0.5.dist-info/WHEEL
translation-1.0.5.dist-info/metadata.json
translation-1.0.5.dist-info/top_level.txt
