Metadata-Version: 1.1
Name: translation
Version: 1.0.5
Summary: A translation package
Home-page: https://github.com/littlecodersh/translation
Author: LittleCoder
Author-email: i7meavnktqegm1b@qq.com
License: MIT
Keywords: translate translation
Platform: UNKNOWN
Classifier: Development Status :: 3 - Alpha
Classifier: Intended Audience :: Developers
Classifier: Topic :: Software Development :: Libraries :: Python Modules
Classifier: License :: OSI Approved :: MIT License
Classifier: Programming Language :: Python :: 2.7
Classifier: Programming Language :: Python :: 3.5
